LICENSE
MANIFEST.in
README.rst
setup.py
account/__init__.py
account/admin.py
account/apps.py
account/models.py
account/providers.py
account/urls.py
account/views.py
account/migrations/0001_initial.py
account/migrations/0002_auto_20170101_1054.py
account/migrations/0003_auto_20170101_1221.py
account/migrations/0004_auto_20170101_1222.py
account/migrations/__init__.py
account/static/.gitkeep
account/templates/.gitkeep
django_student_oauth.egg-info/PKG-INFO
django_student_oauth.egg-info/SOURCES.txt
django_student_oauth.egg-info/dependency_links.txt
django_student_oauth.egg-info/requires.txt
django_student_oauth.egg-info/top_level.txt
docs/.gitkeep